{
    "56-year-old who recently joined a gym": "The patient is here indicating that she has joined a gym.",
    "presents with chest discomfort": "She has been experiencing chest discomfort",
    "heaviness": "heavyness with dyspnea on exertion.",
    "shortness of breath during exercise": "dyspnea on exertion.",
    "sore throat": "She also complains of sore throat",
    "and cough": "cough.",
    "medical history includes coronary vasospastic events": "Coronary vasospastic events",
    "glucose intolerance": "Glucose intolerance with post prandial hyperglycemia.",
    "hyperlipidemia": "Hyperlipidemia.",
    "hypertension": "Hypertension.",
    "obesity": "Obesity.",
    "symptoms of chest pressure and dyspnea during exertion": "chest discomfort and heavyness with dyspnea on exertion.",
    "suspicion of symptomatic cardiac ischemia": "The symptoms that she describes suggest possible symptomatic cardiac ischemia.",
    "not unstable angina": "The description of symptoms do not suggest unstable angina.",
    "normal baseline ECG taken during the visit": "She had a baseline ECG today in my office that was normal.",
    "plan includes follow-up with cardiology for further assessment": "I have instructed the patient to follow up with cardiology for further assessment",
    "exercise tolerance test (ETT)": "and an ETT.",
    "continued management of glucose intolerance": "Continue metformin, well tolerated, HbA1c requested.",
    "continued management of hyperlipidemia": "On atorvastatin. Target LDL <70, new values requested.",
    "continued management of hypertension with existing medications": "Hypertension. Stable, continue current medications.",
    "Rhinopharyngitis is being treated with amoxicillin and fluticasone": "Rhinopharyngitis. Amoxicillin and fluticasone initiated.",
    "Additional follow-ups for gynecology": "Bone densitometry requested. Labs requested.",
    "ophthalmology": "Follow up after tests or in 3-6 months.",
    "bone densitometry": "Bone densitometry requested.",
    "lab tests recommended": "Labs requested. Follow up after tests or in 3-6 months."
}
